filerunner/__init__.py
filerunner/base.py
filerunner/utils.py
filerunner-1.1.0.dist-info/licenses/LICENSE
filerunner-1.1.0.dist-info/METADATA
filerunner-1.1.0.dist-info/WHEEL
filerunner-1.1.0.dist-info/top_level.txt
filerunner-1.1.0.dist-info/RECORD
