Metadata-Version: 2.4
Name: filerunner
Version: 1.1.0
Summary: Quickly process files.
Requires-Python: >=3.10
License-File: LICENSE
Requires-Dist: rich>=14.2.0
Dynamic: license-file
